mugicli/__init__.py
mugicli/head.py
mugicli/pycat.py
mugicli/pycol.py
mugicli/pycwd.py
mugicli/pydos2unix.py
mugicli/pydu.py
mugicli/pyecho.py
mugicli/pyextstat.py
mugicli/pyfalse.py
mugicli/pyfor.py
mugicli/pyfree.py
mugicli/pygrep.py
mugicli/pyhead.py
mugicli/pyiconv.py
mugicli/pyls.py
mugicli/pymd5sum.py
mugicli/pymtime.py
mugicli/pymtimestat.py
mugicli/pynmap.py
mugicli/pynth.py
mugicli/pyplot.py
mugicli/pyprintcmd.py
mugicli/pyrandom.py
mugicli/pysed.py
mugicli/pyseq.py
mugicli/pysetpath.py
mugicli/pysha1sum.py
mugicli/pysha224sum.py
mugicli/pysha256sum.py
mugicli/pysha384sum.py
mugicli/pysha512sum.py
mugicli/pysleep.py
mugicli/pysort.py
mugicli/pystart.py
mugicli/pytail.py
mugicli/pytime.py
mugicli/pytmp.py
mugicli/pytouch.py
mugicli/pytr.py
mugicli/pytree.py
mugicli/pytrue.py
mugicli/pyuniq.py
mugicli/pyunix2dos.py
mugicli/pyuptime.py
mugicli/pywc.py
mugicli/pyxargs.py
mugicli/pyxxd.py
mugicli/pyzip.py
mugicli/shared.py
mugicli/template.py
mugicli/test.py
mugicli/pyexec/__init__.py
mugicli/pyexec/__main__.py
mugicli/pyexec/chain.py
mugicli/pyexec/split.py
mugicli/pyfind/__init__.py
mugicli/pyfind/__main__.py
mugicli/pyfind/action.py
mugicli/pyfind/executor.py
mugicli/pyfind/node.py
mugicli/pyfind/parse.py
mugicli/pyfind/predicate.py
mugicli/pyfind/tok.py
mugicli-0.0.35.dist-info/LICENSE
mugicli-0.0.35.dist-info/METADATA
mugicli-0.0.35.dist-info/WHEEL
mugicli-0.0.35.dist-info/entry_points.txt
mugicli-0.0.35.dist-info/top_level.txt
mugicli-0.0.35.dist-info/RECORD
