Metadata-Version: 2.2
Name: mugicli
Version: 0.0.35
Summary: Shell utilities resembling coreutils, small, extendable and windows-friendly
Home-page: https://github.com/mugiseyebrows/mugi-cli
Author: Stanislav Doronin
Author-email: mugisbrows@gmail.com
License-File: LICENSE
Requires-Dist: python-dateutil
Requires-Dist: bashrange
Requires-Dist: chardet
Requires-Dist: shortwalk
Dynamic: author
Dynamic: author-email
Dynamic: description
Dynamic: description-content-type
Dynamic: home-page
Dynamic: requires-dist
Dynamic: summary
